README.md
setup.cfg
setup.py
AiogramStorages/__init__.py
AiogramStorages/storages.py
AiogramStorages.egg-info/PKG-INFO
AiogramStorages.egg-info/SOURCES.txt
AiogramStorages.egg-info/dependency_links.txt
AiogramStorages.egg-info/requires.txt
AiogramStorages.egg-info/top_level.txt