Metadata-Version: 2.1
Name: AiogramStorages
Version: 1.0.0
Summary: Save your data and states in aiogram bot.Aiogram-storages was created to extend the standard fsm_storage options in aiogram.
Home-page: https://github.com/DIMFLIX-OFFICIAL/AiogramStorages
Author: DIMFLIX
Author-email: dimflix.official@gmail.ru
License: MIT License
Download-URL: https://github.com/DIMFLIX-OFFICIAL/AiogramStorages/archive/refs/heads/main.zip
Platform: UNKNOWN
Classifier: Operating System :: OS Independent
Classifier: Intended Audience :: End Users/Desktop
Classifier: Intended Audience :: Developers
Classifier: Programming Language :: Python
Classifier: Programming Language :: Python :: 3
Classifier: Programming Language :: Python :: 3.6
Classifier: Programming Language :: Python :: 3.7
Classifier: Programming Language :: Python :: 3.8
Classifier: Programming Language :: Python :: 3.9
Classifier: Programming Language :: Python :: 3.10
Classifier: Programming Language :: Python :: 3.11
Classifier: Programming Language :: Python :: Implementation :: PyPy
Classifier: Programming Language :: Python :: Implementation :: CPython
